data.py
efx.py
game.py
sides.py
start.py
gHangman-1.1.1.data/data/Words.dat
gHangman-1.1.1.dist-info/LICENSE
gHangman-1.1.1.dist-info/METADATA
gHangman-1.1.1.dist-info/WHEEL
gHangman-1.1.1.dist-info/entry_points.txt
gHangman-1.1.1.dist-info/top_level.txt
gHangman-1.1.1.dist-info/RECORD
