Metadata-Version: 2.1
Name: gHangman
Version: 1.1.1
Summary: A classical word guessing game.
Home-page: https://github.com/a-good-omen/hangman-remastered
Author: a-good-omen
Author-email: student.rohn@gmail.com
Classifier: Programming Language :: Python :: 3
Classifier: License :: OSI Approved :: MIT License
Classifier: Operating System :: OS Independent
Requires-Python: >=3.7
License-File: LICENSE
